hoodex/__init__.py
hoodex/cli.py
hoodex/main.py
hoodex/plex.py
hoodex-0.1.2.dist-info/AUTHORS.rst
hoodex-0.1.2.dist-info/LICENSE
hoodex-0.1.2.dist-info/METADATA
hoodex-0.1.2.dist-info/WHEEL
hoodex-0.1.2.dist-info/entry_points.txt
hoodex-0.1.2.dist-info/top_level.txt
hoodex-0.1.2.dist-info/RECORD
