Metadata-Version: 2.1
Name: hoodex
Version: 0.1.2
Summary: Hoodex checks your plex instance and get the url of the latest uploaded content
Home-page: https://github.com/Ratxi/hoodex
Author: Ratxi
Author-email: ratxi.com@gmail.com
License: Apache Software License 2.0
Keywords: hoodex
Platform: UNKNOWN
Classifier: Development Status :: 2 - Pre-Alpha
Classifier: Intended Audience :: Developers
Classifier: License :: OSI Approved :: Apache Software License
Classifier: Natural Language :: English
Classifier: Programming Language :: Python :: 2
Classifier: Programming Language :: Python :: 2.7
Classifier: Programming Language :: Python :: 3
Classifier: Programming Language :: Python :: 3.4
Classifier: Programming Language :: Python :: 3.5
Classifier: Programming Language :: Python :: 3.6
Classifier: Programming Language :: Python :: 3.7
Requires-Dist: Click (>=6.0)
Requires-Dist: PlexAPI (==3.1.0)
